teedoc_plugin_google_translate/__init__.py
teedoc_plugin_google_translate/assets/cleardot.gif
teedoc_plugin_google_translate/assets/element.js
teedoc_plugin_google_translate/assets/element_main.js
teedoc_plugin_google_translate/assets/main.js
teedoc_plugin_google_translate/assets/translate.svg
teedoc_plugin_google_translate-1.1.6.dist-info/LICENSE
teedoc_plugin_google_translate-1.1.6.dist-info/METADATA
teedoc_plugin_google_translate-1.1.6.dist-info/WHEEL
teedoc_plugin_google_translate-1.1.6.dist-info/top_level.txt
teedoc_plugin_google_translate-1.1.6.dist-info/RECORD
